kv_progrid-0.1.2.dist-info/DESCRIPTION.rst
kv_progrid-0.1.2.dist-info/WHEEL
kv_progrid-0.1.2.dist-info/top_level.txt
kv_progrid-0.1.2.dist-info/metadata.json
kv_progrid-0.1.2.dist-info/METADATA
kv_progrid-0.1.2.dist-info/RECORD
progrid/progrid.kv
progrid/demo.py
progrid/progrid.py
progrid/__init__.py
