Metadata-Version: 2.0
Name: kv-progrid
Version: 0.1.2
Summary: Easy to use grid for kivy.
Home-page: https://github.com/Cuuuurzel/kivy-pro-grid
Author: Federico Curzel
Author-email: cuuuurzel@gmail.com
License: UNKNOWN
Platform: UNKNOWN
